{
  "id": "c-014",
  "title": "Prompt换框法：同一个问题，换个取景框",
  "date": "2026.04",
  "type": "insight",
  "tags": [
    "我提炼的方法论",
    "Prompt换框"
  ],
  "excerpt": "AI培训中的核心方法论——当AI给出的答案不满意时，不要换工具，换'取景框'。从'这是什么'换成'这不是什么'，从'怎么做'变成'为什么不做'。一种思维体操，让非技术同事快速掌握与AI对话的窍门。",
  "content": "在培训非技术同事用AI的过程中，我发现最常见的挫败感是：'我问了，但AI答得不好'。\n\n大多数人的第一反应是换模型、加提示词、或者放弃。但其实更有效的方法是：换一个问题框架。\n\n我把这个方法提炼为'Prompt换框法'。\n\n【六种常用取景框】\n\n1. 是什么 → 这不是什么\n   例：'什么是好产品？' → '好产品不会犯哪些错误？'\n\n2. 怎么做 → 为什么不做\n   例：'怎么提高用户留存？' → '为什么用户会流失？'\n\n3. 优点是什么 → 风险是什么\n   例：'这个方案的优点？' → '这个方案可能在哪里失败？'\n\n4. 给我一个方案 → 给我三个不同方案\n   例：'怎么推广这个活动？' → '请给保守/激进/低成本三个版本'\n\n5. 从整体看 → 从边缘案例看\n   例：'我们的用户画像是什么？' → '哪些用户最可能被我们忽略？'\n\n6. 从结果出发 → 从过程出发\n   例：'怎么做到月活100万？' → '月活100万的团队每天做什么决策？'\n\n【训练方式】\n我设计了一套练习：给同一个业务问题，让同事用三种不同取景框问AI，然后比较答案差异。大多数人练完会发现：不是AI不行，是自己的问题太窄。\n\n【核心洞察】\nAI的回答质量 = 问题的信息熵 × 框架的清晰度。换框不是在技巧层面优化提示词，是在认知层面扩展你的思考角度。",
  "images": [
    "/images/cases/prompt-reframing.jpg"
  ]
}
